[
  {
    "photo": "/images/avatar-placeholder-medz.png",
    "firstName": "Lilo",
    "lastName": "Stitch",
    "birthday": "fdghdfghdf",
    "conditions": "fdghdfgh",
    "medications": "dfghdfgh",
    "allergies": "dfghdfghdfgh",
    "contacts": "fgdhdfghdfgh",
    "timestamp": 1643084269448,
    "id": "7aa69cd5-910e-4479-bca8-1164d832402e"
  },
  {
    "photo": "/images/avatar-placeholder-medz.png",
    "firstName": "Kenny",
    "middleName": "",
    "lastName": "Gee",
    "gender": "",
    "birthday": "24/09/1987",
    "bloodType": "B-",
    "height": "",
    "weight": "",
    "conditions": "Asthma",
    "medications": "Ventolin",
    "allergies": "Peanuts (hives)",
    "doctor": "Dr. J. Thorpe, Apex Medical",
    "contacts": "June 234-987-0987",
    "notes": "",
    "timestamp": 1643176939605,
    "id": "bd719c15-afed-4949-a5a7-d2ac1fb1aaf3"
  },
  {
    "photo": "/images/avatar-placeholder-medz.png",
    "firstName": "cursor test",
    "middleName": "",
    "lastName": "sdcdvdfv",
    "gender": "",
    "birthday": "2026-02-07",
    "bloodType": "",
    "height": "",
    "weight": "",
    "conditions": "dfvdfvfvdfv",
    "medications": "wdwdf",
    "allergies": "dvdfvfv",
    "doctor": "",
    "contacts": "feferf",
    "notes": "",
    "timestamp": 1770486190593,
    "id": "46b889c4-9240-4604-9110-38ee8aaaa16b"
  },
  {
    "photo": "/images/profile-e3c7713e-bb18-4d2c-b94b-6bcb4b909a24.jpg",
    "firstName": "Test pic",
    "middleName": "sdsdfsdf",
    "lastName": "sdsdfsdf",
    "gender": "",
    "birthday": "2026-02-07",
    "bloodType": "",
    "height": "",
    "weight": "",
    "conditions": "sdsdfsdf",
    "medications": "sdsdfsdf",
    "allergies": "sdsdfsdf",
    "doctor": "",
    "contacts": "sdsdfsdf",
    "notes": "",
    "timestamp": 1770491546877,
    "id": "4e62527d-b95c-4df7-9fee-4a4a957d4de0"
  }
]